coredotfinance/__init__.py
coredotfinance/data.py
coredotfinance/binance/__init__.py
coredotfinance/binance/api.py
coredotfinance/binance/binance.py
coredotfinance/binance/dataframe_util.py
coredotfinance/binance/datetime_util.py
coredotfinance/binance/utils.py
coredotfinance/database/__init__.py
coredotfinance/database/krx_db.py
coredotfinance/krx/__init__.py
coredotfinance/krx/api/__init__.py
coredotfinance/krx/api/data_reader.py
coredotfinance/krx/api/tool.py
coredotfinance/krx/core/__init__.py
coredotfinance/krx/core/classify.py
coredotfinance/krx/core/column.py
coredotfinance/krx/core/eng2kor.json
coredotfinance/krx/core/fetch.py
coredotfinance/krx/core/function_code_list.py
coredotfinance/krx/core/jsp_util.py
coredotfinance/krx/core/kor2eng.json
coredotfinance/krx/core/option.py
coredotfinance/krx/core/process.py
coredotfinance/krx/core/webio.py
coredotfinance/krx/core/jsp/MDCSTAT001.jsp
coredotfinance/krx/core/jsp/MDCSTAT002.jsp
coredotfinance/krx/core/jsp/MDCSTAT003.jsp
coredotfinance/krx/core/jsp/MDCSTAT010.jsp
coredotfinance/krx/core/jsp/MDCSTAT012.jsp
coredotfinance/krx/core/jsp/MDCSTAT015.jsp
coredotfinance/krx/core/jsp/MDCSTAT016.jsp
coredotfinance/krx/core/jsp/MDCSTAT017.jsp
coredotfinance/krx/core/jsp/MDCSTAT023.jsp
coredotfinance/krx/core/jsp/MDCSTAT035.jsp
coredotfinance/krx/core/jsp/MDCSTAT037.jsp
coredotfinance/krx/core/jsp/MDCSTAT039.jsp
coredotfinance/krx/core/jsp/MDCSTAT043.jsp
coredotfinance/krx/core/jsp/MDCSTAT045.jsp
coredotfinance/krx/core/jsp/MDCSTAT064.jsp
coredotfinance/krx/core/jsp/MDCSTAT066.jsp
coredotfinance/krx/core/jsp/MDCSTAT083.jsp
coredotfinance/krx/core/jsp/MDCSTAT084.jsp
coredotfinance/krx/core/jsp/__init__.py
coredotfinance/krx/core/krx_website/__init__.py
coredotfinance/krx/core/krx_website/bond.py
coredotfinance/krx/core/krx_website/commodity.py
coredotfinance/krx/core/krx_website/derivative.py
coredotfinance/krx/core/krx_website/index.py
coredotfinance/krx/core/krx_website/info.py
coredotfinance-1.2.4.dist-info/LICENSE
coredotfinance-1.2.4.dist-info/METADATA
coredotfinance-1.2.4.dist-info/WHEEL
coredotfinance-1.2.4.dist-info/top_level.txt
coredotfinance-1.2.4.dist-info/RECORD
