Metadata-Version: 2.1
Name: coredotfinance
Version: 1.2.4
Summary: Financial data on web
Home-page: https://github.com/coredottoday/CoreDotFinance
Author: Core.Today
Author-email: help@core.today
License: UNKNOWN
Keywords: finance,stock,money,krx,bitcoin,cryptocurrency,index
Platform: UNKNOWN
Requires-Dist: pandas (>=0.14)
Requires-Dist: numpy (>=1.8)
Requires-Dist: requests (>=2.7.0)
Requires-Dist: beautifulsoup4 (>=4.9.3)
Requires-Dist: plotly (>=4.14.3)
